MANIFEST.in
README.rst
setup.py
easyply/__init__.py
easyply/nodes.py
easyply/parser.py
easyply.egg-info/PKG-INFO
easyply.egg-info/SOURCES.txt
easyply.egg-info/dependency_links.txt
easyply.egg-info/requires.txt
easyply.egg-info/top_level.txt
test/test_easyply.py
test/test_issue2.py