Metadata-Version: 1.1
Name: easyply
Version: 1.2
Summary: Helper functions for PLY (Python Lex & Yacc)
Home-page: https://github.com/MHordecki/easyply
Author: Mike Hordecki
Author-email: mike@hordecki.com
License: UNKNOWN
Platform: UNKNOWN
Classifier: Programming Language :: Python
Classifier: Programming Language :: Python :: 3
Classifier: License :: OSI Approved :: MIT License
Classifier: Operating System :: OS Independent
Classifier: Development Status :: 3 - Alpha
Classifier: Intended Audience :: Developers
Classifier: Topic :: Software Development :: Libraries :: Python Modules
